{
  "name": "Neobrutalism Dark",
  "type": "dark",
  "colors": {
    "activityBar.background": "#FF0000",
    "activityBar.border": "#FFFFFF",
    "activityBar.foreground": "#000000",
    "activityBar.inactiveForeground": "#333333",
    "activityBarBadge.background": "#000000",
    "activityBarBadge.foreground": "#FFFFFF",
    "activityBar.activeBorder": "#FFFFFF",
    "activityBar.activeBackground": "#FF0000",

    "sideBar.background": "#000000",
    "sideBar.border": "#FFFFFF",
    "sideBar.foreground": "#FFFFFF",
    "sideBarTitle.foreground": "#FFFFFF",
    "sideBarSectionHeader.background": "#FFFF00",
    "sideBarSectionHeader.foreground": "#000000",
    "sideBarSectionHeader.border": "#FFFFFF",

    "list.activeSelectionBackground": "#FFFF00",
    "list.activeSelectionForeground": "#000000",
    "list.inactiveSelectionBackground": "#000000",
    "list.inactiveSelectionForeground": "#FFFFFF",
    "list.hoverBackground": "#000000",
    "list.hoverForeground": "#FFFFFF",
    "list.focusBackground": "#FFFF00",
    "list.focusForeground": "#000000",
    "list.highlightForeground": "#FF0000",
    "list.dropBackground": "#00FF0040",

    "tree.indentGuidesStroke": "#FFFFFF",

    "titleBar.activeBackground": "#0000FF",
    "titleBar.activeForeground": "#000000",
    "titleBar.inactiveBackground": "#0000FF",
    "titleBar.inactiveForeground": "#333333",
    "titleBar.border": "#FFFFFF",

    "menu.background": "#000000",
    "menu.foreground": "#FFFFFF",
    "menu.selectionBackground": "#FFFF00",
    "menu.selectionForeground": "#000000",
    "menu.selectionBorder": "#FFFFFF",
    "menu.separatorBackground": "#FFFFFF",

    "menubar.selectionBackground": "#FFFF00",
    "menubar.selectionForeground": "#000000",

    "editor.background": "#000000",
    "editor.foreground": "#FFFFFF",
    "editorLineNumber.foreground": "#666666",
    "editorLineNumber.activeForeground": "#FF0000",
    "editorCursor.foreground": "#FFFF00",
    "editor.selectionBackground": "#FFFF0040",
    "editor.selectionHighlightBackground": "#FFFF0030",
    "editor.wordHighlightBackground": "#FFFF0030",
    "editor.wordHighlightStrongBackground": "#FFFF0040",
    "editor.findMatchBackground": "#00FF0040",
    "editor.findMatchHighlightBackground": "#00FF0030",
    "editor.findRangeHighlightBackground": "#FFFF0020",
    "editor.inactiveSelectionBackground": "#FFFF0020",
    "editor.hoverHighlightBackground": "#FFD93D35",
    "editor.hoverWidget.background": "#000000",
    "editor.hoverWidget.border": "#FFFFFF",
    "editor.lineHighlightBackground": "#000000",
    "editor.lineHighlightBorder": "#FFFFFF",
    "editor.rangeHighlightBackground": "#FFFF0020",
    "editor.symbolHighlightBackground": "#FFD93D35",
    "editorWhitespace.foreground": "#444444",
    "editorIndentGuide.background": "#FFFFFF",
    "editorIndentGuide.activeBackground": "#FF0000",
    "editorRuler.foreground": "#FFFFFF",
    "editorCodeLens.foreground": "#666666",
    "editorBracketMatch.background": "#00FF0030",
    "editorBracketMatch.border": "#FFFFFF",

    "editorGroup.background": "#FFFF00",
    "editorGroup.border": "#FFFFFF",
    "editorGroup.dropBackground": "#00FF0040",
    "editorGroupHeader.noTabsBackground": "#FFFF00",
    "editorGroupHeader.tabsBackground": "#FFFF00",
    "editorGroupHeader.tabsBorder": "#FFFFFF",
    "editorGroupHeader.border": "#FFFFFF",
    "editorGroup.focusedEmptyBorder": "#FFFFFF",
    "editorGroup.emptyBackground": "#000000",

    "tab.activeBackground": "#000000",
    "tab.activeForeground": "#FFFFFF",
    "tab.activeBorder": "#FF0000",
    "tab.activeBorderTop": "#FFFFFF",
    "tab.inactiveBackground": "#000000",
    "tab.inactiveForeground": "#666666",
    "tab.border": "#FFFFFF",
    "tab.hoverBackground": "#000000",
    "tab.hoverForeground": "#FFFFFF",
    "tab.unfocusedActiveBorder": "#FFFFFF",
    "tab.unfocusedActiveForeground": "#CCCCCC",
    "tab.unfocusedInactiveForeground": "#666666",
    "tab.lastPinnedBorder": "#FFFFFF",

    "panel.background": "#000000",
    "panel.border": "#FFFFFF",
    "panelTitle.activeForeground": "#FFFFFF",
    "panelTitle.activeBorder": "#FF0000",
    "panelTitle.inactiveForeground": "#666666",
    "panelSection.border": "#FFFFFF",
    "panelSectionHeader.background": "#00FF00",
    "panelSectionHeader.foreground": "#000000",

    "statusBar.background": "#FFFF00",
    "statusBar.foreground": "#000000",
    "statusBar.border": "#FFFFFF",
    "statusBar.debuggingBackground": "#FF0000",
    "statusBar.debuggingForeground": "#000000",
    "statusBar.noFolderBackground": "#000000",
    "statusBar.noFolderForeground": "#FFFFFF",
    "statusBarItem.activeBackground": "#FF0000",
    "statusBarItem.hoverBackground": "#FF0000",
    "statusBarItem.prominentBackground": "#0000FF",
    "statusBarItem.prominentForeground": "#000000",
    "statusBarItem.remoteBackground": "#00FF00",
    "statusBarItem.remoteForeground": "#000000",

    "badge.background": "#FF0000",
    "badge.foreground": "#000000",

    "breadcrumbs.background": "#000000",
    "breadcrumbs.foreground": "#666666",
    "breadcrumbs.focusForeground": "#FFFFFF",
    "breadcrumbs.activeSelectionForeground": "#FFFFFF",
    "breadcrumbsPicker.background": "#000000",

    "button.background": "#0000FF",
    "button.foreground": "#000000",
    "button.hoverBackground": "#0000FF",
    "button.secondaryBackground": "#FF0000",
    "button.secondaryForeground": "#000000",
    "button.secondaryHoverBackground": "#FF0000",
    "button.border": "#FFFFFF",

    "checkbox.background": "#000000",
    "checkbox.foreground": "#FFFFFF",
    "checkbox.border": "#FFFFFF",

    "dropdown.background": "#000000",
    "dropdown.foreground": "#FFFFFF",
    "dropdown.border": "#FFFFFF",
    "dropdown.listBackground": "#000000",

    "input.background": "#000000",
    "input.foreground": "#FFFFFF",
    "input.border": "#FFFFFF",
    "input.placeholderForeground": "#666666",
    "inputOption.activeBorder": "#FF0000",
    "inputOption.activeBackground": "#FFFF00",
    "inputOption.activeForeground": "#000000",
    "inputValidation.errorBackground": "#FF0000",
    "inputValidation.errorForeground": "#000000",
    "inputValidation.errorBorder": "#FFFFFF",
    "inputValidation.infoBackground": "#0000FF",
    "inputValidation.infoForeground": "#000000",
    "inputValidation.infoBorder": "#FFFFFF",
    "inputValidation.warningBackground": "#FFFF00",
    "inputValidation.warningForeground": "#000000",
    "inputValidation.warningBorder": "#FFFFFF",

    "scrollbar.shadow": "#00000060",
    "scrollbarSlider.activeBackground": "#FF0000",
    "scrollbarSlider.background": "#FFFFFF60",
    "scrollbarSlider.hoverBackground": "#FF0000",

    "progressBar.background": "#FF0000",

    "quickInput.background": "#000000",
    "quickInput.foreground": "#FFFFFF",
    "quickInputTitle.background": "#FFFF00",

    "pickerGroup.border": "#FFFFFF",
    "pickerGroup.foreground": "#666666",

    "keybindingLabel.background": "#FFFF00",
    "keybindingLabel.foreground": "#000000",
    "keybindingLabel.border": "#FFFFFF",
    "keybindingLabel.bottomBorder": "#FFFFFF",

    "notificationCenter.border": "#FFFFFF",
    "notificationCenterHeader.background": "#FFFF00",
    "notificationCenterHeader.foreground": "#000000",
    "notificationLink.foreground": "#0000FF",
    "notificationToast.border": "#FFFFFF",
    "notifications.background": "#000000",
    "notifications.border": "#FFFFFF",
    "notifications.foreground": "#FFFFFF",
    "notificationBadge.background": "#FF0000",
    "notificationBadge.foreground": "#000000",

    "extensionBadge.remoteBackground": "#0000FF",
    "extensionBadge.remoteForeground": "#000000",
    "extensionBadge.starForeground": "#FFFF00",
    "extensionButton.prominentBackground": "#FF0000",
    "extensionButton.prominentForeground": "#000000",
    "extensionButton.prominentHoverBackground": "#FF0000",

    "welcomePage.background": "#000000",
    "welcomePage.buttonBackground": "#0000FF",
    "welcomePage.buttonHoverBackground": "#0000FF",
    "walkThrough.embeddedEditorBackground": "#000000",

    "peekView.border": "#FFFFFF",
    "peekViewEditor.background": "#000000",
    "peekViewEditorGutter.background": "#FFFF00",
    "peekViewEditor.matchHighlightBackground": "#FFFF0040",
    "peekViewResult.background": "#FFFF00",
    "peekViewResult.fileForeground": "#000000",
    "peekViewResult.lineForeground": "#333333",
    "peekViewResult.matchHighlightBackground": "#FFFF0040",
    "peekViewResult.selectionBackground": "#FF0000",
    "peekViewResult.selectionForeground": "#000000",
    "peekViewTitle.background": "#FFFF00",
    "peekViewTitleDescription.foreground": "#333333",
    "peekViewTitleLabel.foreground": "#000000",

    "merge.currentHeaderBackground": "#00FF0040",
    "merge.currentContentBackground": "#00FF0020",
    "merge.incomingHeaderBackground": "#0000FF40",
    "merge.incomingContentBackground": "#0000FF20",
    "merge.border": "#FFFFFF",
    "merge.commonHeaderBackground": "#FFFF0040",
    "merge.commonContentBackground": "#FFFF0020",

    "editorOverviewRuler.border": "#FFFFFF",
    "editorOverviewRuler.currentContentForeground": "#0000FF",
    "editorOverviewRuler.incomingContentForeground": "#FF0000",
    "editorOverviewRuler.findMatchForeground": "#00FF00",
    "editorOverviewRuler.rangeHighlightForeground": "#FFFF00",
    "editorOverviewRuler.selectionHighlightForeground": "#FF6B6B80",
    "editorOverviewRuler.wordHighlightForeground": "#FFFF0080",
    "editorOverviewRuler.wordHighlightStrongForeground": "#FFFF00",
    "editorOverviewRuler.modifiedForeground": "#0000FF",
    "editorOverviewRuler.addedForeground": "#00FF00",
    "editorOverviewRuler.deletedForeground": "#FF0000",
    "editorOverviewRuler.errorForeground": "#FF0000",
    "editorOverviewRuler.warningForeground": "#FFFF00",
    "editorOverviewRuler.infoForeground": "#0000FF",

    "editorGutter.background": "#000000",
    "editorGutter.modifiedBackground": "#0000FF",
    "editorGutter.addedBackground": "#00FF00",
    "editorGutter.deletedBackground": "#FF0000",
    "editorGutter.commentRangeForeground": "#666666",

    "editorError.foreground": "#FF0000",
    "editorError.border": "#FFFFFF",
    "editorWarning.foreground": "#FFFF00",
    "editorWarning.border": "#FFFFFF",
    "editorInfo.foreground": "#0000FF",
    "editorInfo.border": "#FFFFFF",
    "editorHint.foreground": "#666666",
    "editorHint.border": "#666666",

    "problemsErrorIcon.foreground": "#FF0000",
    "problemsWarningIcon.foreground": "#FFFF00",
    "problemsInfoIcon.foreground": "#0000FF",

    "diffEditor.insertedTextBackground": "#00FF0040",
    "diffEditor.insertedTextBorder": "#00FF00",
    "diffEditor.removedTextBackground": "#FF000040",
    "diffEditor.removedTextBorder": "#FF0000",
    "diffEditor.border": "#FFFFFF",

    "settings.headerForeground": "#FFFFFF",
    "settings.modifiedItemIndicator": "#FF0000",
    "settings.dropdownBackground": "#000000",
    "settings.dropdownForeground": "#FFFFFF",
    "settings.dropdownBorder": "#FFFFFF",
    "settings.checkboxBackground": "#000000",
    "settings.checkboxForeground": "#FFFFFF",
    "settings.checkboxBorder": "#FFFFFF",
    "settings.textInputBackground": "#000000",
    "settings.textInputForeground": "#FFFFFF",
    "settings.textInputBorder": "#FFFFFF",
    "settings.numberInputBackground": "#000000",
    "settings.numberInputForeground": "#FFFFFF",
    "settings.numberInputBorder": "#FFFFFF",
    "settings.focusedItemBackground": "#FFFF00",
    "settings.focusedItemBorder": "#FFFFFF",

    "gitDecoration.addedResourceForeground": "#00FF00",
    "gitDecoration.conflictingResourceForeground": "#FF0000",
    "gitDecoration.deletedResourceForeground": "#FF0000",
    "gitDecoration.ignoredResourceForeground": "#666666",
    "gitDecoration.modifiedResourceForeground": "#FFFF00",
    "gitDecoration.stageModifiedResourceForeground": "#FFFF00",
    "gitDecoration.submoduleResourceForeground": "#0000FF",
    "gitDecoration.untrackedResourceForeground": "#00FF00",

    "debugToolBar.background": "#FFFF00",
    "debugToolBar.border": "#FFFFFF",
    "debugIcon.continueForeground": "#00FF00",
    "debugIcon.disconnectForeground": "#FF0000",
    "debugIcon.pauseForeground": "#FFFF00",
    "debugIcon.restartForeground": "#0000FF",
    "debugIcon.startForeground": "#00FF00",
    "debugIcon.stepBackForeground": "#666666",
    "debugIcon.stepIntoForeground": "#666666",
    "debugIcon.stepOutForeground": "#666666",
    "debugIcon.stepOverForeground": "#666666",
    "debugIcon.stopForeground": "#FF0000",

    "terminal.background": "#000000",
    "terminal.foreground": "#FFFFFF",
    "terminal.ansiBlack": "#000000",
    "terminal.ansiRed": "#FF0000",
    "terminal.ansiGreen": "#00FF00",
    "terminal.ansiYellow": "#FFFF00",
    "terminal.ansiBlue": "#0000FF",
    "terminal.ansiMagenta": "#000000",
    "terminal.ansiCyan": "#00FF00",
    "terminal.ansiWhite": "#666666",
    "terminal.ansiBrightBlack": "#333333",
    "terminal.ansiBrightRed": "#FF0000",
    "terminal.ansiBrightGreen": "#00FF00",
    "terminal.ansiBrightYellow": "#FFFF00",
    "terminal.ansiBrightBlue": "#0000FF",
    "terminal.ansiBrightMagenta": "#000000",
    "terminal.ansiBrightCyan": "#00FF00",
    "terminal.ansiBrightWhite": "#FFFFFF",
    "terminal.selectionBackground": "#FFFF0040",
    "terminalCursor.background": "#FFFF00",
    "terminalCursor.foreground": "#FFFF00",

    "debugConsole.infoForeground": "#FFFFFF",
    "debugConsole.warningForeground": "#FFFF00",
    "debugConsole.errorForeground": "#FF0000",
    "debugConsole.sourceForeground": "#666666",
    "debugConsoleInputIcon.foreground": "#0000FF",

    "minimap.background": "#000000",
    "minimap.errorHighlight": "#FF0000",
    "minimap.findMatchHighlight": "#00FF00",
    "minimap.selectionHighlight": "#FFFF0040",
    "minimap.warningHighlight": "#FFFF00",
    "minimapSlider.background": "#FFFFFF40",
    "minimapSlider.hoverBackground": "#FFFFFF60",
    "minimapSlider.activeBackground": "#FF0000",

    "editorWidget.background": "#000000",
    "editorWidget.border": "#FFFFFF",
    "editorWidget.foreground": "#FFFFFF",
    "editorWidget.resizeBorder": "#FFFFFF",

    "suggestWidget.background": "#000000",
    "suggestWidget.border": "#FFFFFF",
    "suggestWidget.foreground": "#FFFFFF",
    "suggestWidget.highlightForeground": "#FF0000",
    "suggestWidget.selectedBackground": "#FFFF00",
    "suggestWidget.selectedForeground": "#000000",

    "parameterHints.background": "#000000",
    "parameterHints.foreground": "#FFFFFF",

    "symbolIcon.arrayForeground": "#FFFF00",
    "symbolIcon.booleanForeground": "#FF0000",
    "symbolIcon.classForeground": "#0000FF",
    "symbolIcon.colorForeground": "#FF0000",
    "symbolIcon.constantForeground": "#FF0000",
    "symbolIcon.constructorForeground": "#0000FF",
    "symbolIcon.enumeratorForeground": "#FFFF00",
    "symbolIcon.enumeratorMemberForeground": "#FFFF00",
    "symbolIcon.eventForeground": "#FF0000",
    "symbolIcon.fieldForeground": "#0000FF",
    "symbolIcon.fileForeground": "#666666",
    "symbolIcon.folderForeground": "#666666",
    "symbolIcon.functionForeground": "#0000FF",
    "symbolIcon.interfaceForeground": "#0000FF",
    "symbolIcon.keyForeground": "#FF0000",
    "symbolIcon.keywordForeground": "#000000",
    "symbolIcon.methodForeground": "#0000FF",
    "symbolIcon.moduleForeground": "#666666",
    "symbolIcon.namespaceForeground": "#666666",
    "symbolIcon.nullForeground": "#000000",
    "symbolIcon.numberForeground": "#FFFF00",
    "symbolIcon.objectForeground": "#0000FF",
    "symbolIcon.operatorForeground": "#000000",
    "symbolIcon.packageForeground": "#666666",
    "symbolIcon.propertyForeground": "#0000FF",
    "symbolIcon.referenceForeground": "#666666",
    "symbolIcon.snippetForeground": "#666666",
    "symbolIcon.stringForeground": "#00FF00",
    "symbolIcon.structForeground": "#0000FF",
    "symbolIcon.textForeground": "#FFFFFF",
    "symbolIcon.typeParameterForeground": "#FFFF00",
    "symbolIcon.unitForeground": "#FFFF00",
    "symbolIcon.variableForeground": "#0000FF",

    "charts.foreground": "#FFFFFF",
    "charts.lines": "#0000FF",
    "charts.red": "#FF0000",
    "charts.blue": "#0000FF",
    "charts.yellow": "#FFFF00",
    "charts.orange": "#FF9F45",
    "charts.green": "#00FF00",
    "charts.purple": "#000000",

    "ports.iconRunningProcessForeground": "#00FF00",
    "ports.iconPortForeground": "#0000FF",

    "toolbar.activeBackground": "#FFFF00",
    "toolbar.hoverBackground": "#000000",
    "toolbar.hoverOutline": "#FFFFFF"
  },
  "tokenColors": [
    {
      "name": "Comments",
      "scope": ["comment", "punctuation.definition.comment"],
      "settings": {
        "fontStyle": "italic",
        "foreground": "#666666"
      }
    },
    {
      "name": "Keywords",
      "scope": ["keyword", "storage.type", "storage.modifier"],
      "settings": {
        "foreground": "#FF0000"
      }
    },
    {
      "name": "Strings",
      "scope": ["string", "string.quoted", "string.template"],
      "settings": {
        "foreground": "#00FF00"
      }
    },
    {
      "name": "Numbers",
      "scope": ["constant.numeric"],
      "settings": {
        "foreground": "#FFFF00"
      }
    },
    {
      "name": "Functions",
      "scope": ["entity.name.function", "support.function"],
      "settings": {
        "foreground": "#0000FF"
      }
    },
    {
      "name": "Classes",
      "scope": ["entity.name.class", "entity.name.type.class", "support.class"],
      "settings": {
        "foreground": "#FF0000"
      }
    },
    {
      "name": "Variables",
      "scope": ["variable", "identifier", "entity.name.variable"],
      "settings": {
        "foreground": "#FFFFFF"
      }
    },
    {
      "name": "Constants",
      "scope": ["constant", "variable.other.constant", "support.constant"],
      "settings": {
        "foreground": "#FFFF00"
      }
    },
    {
      "name": "Tags",
      "scope": ["entity.name.tag"],
      "settings": {
        "foreground": "#FF0000"
      }
    },
    {
      "name": "Attributes",
      "scope": ["entity.other.attribute-name"],
      "settings": {
        "foreground": "#FF0000"
      }
    },
    {
      "name": "Types",
      "scope": ["entity.name.type", "support.type"],
      "settings": {
        "foreground": "#0000FF"
      }
    },
    {
      "name": "Operators",
      "scope": ["keyword.operator"],
      "settings": {
        "foreground": "#FF0000"
      }
    },
    {
      "name": "Built-ins",
      "scope": ["support.function.builtin", "support.variable"],
      "settings": {
        "foreground": "#00FF00"
      }
    },
    {
      "name": "Punctuation",
      "scope": ["punctuation"],
      "settings": {
        "foreground": "#CCCCCC"
      }
    },
    {
      "name": "Invalid",
      "scope": ["invalid"],
      "settings": {
        "foreground": "#FF0000"
      }
    }
  ],
  "semanticHighlighting": true
}
